ace/__init__.py
ace/ace.py
ace/model.py
ace/smoother.py
ace/supersmoother.py
ace/samples/__init__.py
ace/samples/breiman85.py
ace/samples/smoother_friedman82.py
ace/samples/supersmoother_friedman82.py
ace/samples/wang04.py
ace/tests/__init__.py
ace/tests/test_ace.py
ace/tests/test_model.py
ace/tests/test_smoother.py
ace/validation/__init__.py
ace/validation/validate_smoothers.py
ace-0.3.3.dist-info/LICENSE
ace-0.3.3.dist-info/METADATA
ace-0.3.3.dist-info/WHEEL
ace-0.3.3.dist-info/top_level.txt
ace-0.3.3.dist-info/RECORD
